{
  "name": "LocalizedNinthStratagem",
  "fields": [
    {
      "fieldName": "name",
      "fieldType": "String"
    },
    {
      "fieldName": "summary",
      "fieldType": "String"
    },
    {
      "fieldName": "description",
      "fieldType": "byte[]",
      "fieldTypeBlobContent": "text"
    },
    {
      "fieldName": "keywords",
      "fieldType": "byte[]",
      "fieldTypeBlobContent": "text"
    },
    {
      "fieldName": "language",
      "fieldType": "Language",
      "fieldValues": "EN (English),FR (French),AR (Arabic),ZH (Chinese),DA (Danish),NL (Dutch),FI (Finnish),DE (German),EL (Greek),HU (Hungarian),IS (Icelandic),ID (Indonesian),GA (Irish),IT (Italian),JA (Japanese),KO (Korean),FA (Persian),PL (Polish),PT (Portuguese),RO (Romanian),RU (Russian),SR (Serbian),ES (Spanish),SV (Swedish),TR (Turkish)",
      "fieldValidateRules": [
        "required"
      ]
    }
  ],
  "relationships": [
    {
      "relationshipType": "many-to-one",
      "otherEntityName": "ninthStratagem",
      "otherEntityRelationshipName": "localizations",
      "relationshipValidateRules": "required",
      "relationshipName": "stratagem",
      "otherEntityField": "id"
    }
  ],
  "changelogDate": "20200908200712",
  "entityTableName": "localized_ninth_stratagem",
  "dto": "no",
  "pagination": "no",
  "service": "no",
  "jpaMetamodelFiltering": false,
  "fluentMethods": true,
  "readOnly": false,
  "embedded": false,
  "clientRootFolder": "",
  "applications": "*"
}
